ring_buffer/rtl/ring_flasher.sv
module counter
    import ring_flasher_pkg::*;
(
    //system
    input logic clk, rst_n,

    //signal
    output logic tick
);
    //ffs
    logic [TICK_WIDTH-1:0] cnt;

    //output
    assign tick = (cnt == TICK_MAX-1) ? 1 : 0;

    always_ff @(posedge clk or negedge rst_n) begin
        if (!rst_n)
            cnt <= '0;
        else if (tick)
            cnt <= '0;
        else
            cnt <= cnt + 1;
    end
endmodule

module ring_flasher
    import ring_flasher_pkg::*;
(
    //system
    input logic clk, rst_n,
    input logic rep,

    output logic [NUM_LEDS-1:0] leds
);
    //FSM
    state_t state, next_state;

    //tick from counter instance
    logic tick;
    counter u_counter (
        .clk   (clk),
        .rst_n (rst_n),
        .tick  (tick)
    );

    //step counter
    logic [STEP_WIDTH-1:0]  step_cnt;

    always_ff @(posedge clk or negedge rst_n) begin
        if (!rst_n)
            step_cnt    <= '0;
        else if (tick) begin
            if (state != next_state)
                step_cnt    <= '0;
            else
                step_cnt    <= step_cnt + 1;
        end
    end

    //position pointer
    logic [POS_WIDTH-1:0]   pos_ptr;

    //next_pos combinational — brightness update
    logic [POS_WIDTH-1:0] next_pos;
    always_comb begin
        case (state)
            FORWARD:  next_pos = (pos_ptr + 1) % NUM_LEDS;
            BACKWARD: next_pos = (pos_ptr - 1 + NUM_LEDS) % NUM_LEDS;
            default:  next_pos = pos_ptr;
        endcase
    end

    always_ff @(posedge clk or negedge rst_n) begin
        if (!rst_n)
            pos_ptr <= NUM_LEDS - 1;    //forward tick dau
        else if (tick)
            pos_ptr <= next_pos;
    end

    //brightness registers
    logic [BRIGHT_WIDTH-1:0] led_brightness [NUM_LEDS];

    always_ff @(posedge clk or negedge rst_n) begin
        if (!rst_n) begin
            for (int i = 0; i < NUM_LEDS; i++)
                led_brightness[i] <= '0;
        end else if (tick) begin
            case (state)
                FORWARD, BACKWARD: begin
                    for (int i = 0; i < NUM_LEDS; i++) begin
                        if (i == int'(next_pos))
                            led_brightness[i] <= BRIGHTNESS_LEVELS;
                        else if (led_brightness[i] > 0)
                            led_brightness[i] <= led_brightness[i] - 1;
                    end
                end

                DECAY: begin
                    for (int i = 0; i < NUM_LEDS; i++) begin
                        if (led_brightness[i] > 0)
                            led_brightness[i] <= led_brightness[i] - 1;
                    end
                end

                default: ; 
            endcase
        end
    end

    //all_off in DECAY -> IDLE trigger
    logic all_off;

    always_comb begin
        all_off = 1'b1;

        for (int i = 0; i < NUM_LEDS; i++)
            if (led_brightness[i] != '0)
                all_off = 1'b0;
    end

    //PWM counter: 0..BRIGHTNESS_LEVELS-1
    logic [BRIGHT_WIDTH-1:0] pwm_cnt;

    always_ff @(posedge clk or negedge rst_n) begin
        if (!rst_n)
            pwm_cnt <= '0;
        else if (pwm_cnt == BRIGHTNESS_LEVELS - 1)
            pwm_cnt <= '0;
        else
            pwm_cnt <= pwm_cnt + 1;
    end

    //LED output: led[i] on khi brightness[i] > pwm_cnt
    genvar g;
    generate
        for (g = 0; g < NUM_LEDS; g++) begin : gen_led
            assign leds[g] = (led_brightness[g] > pwm_cnt);
        end
    endgenerate

    //next state fsm
    always_ff @(posedge clk or negedge rst_n) begin
        if (!rst_n)
            state   <= IDLE;
        else
            state   <= next_state;
    end

    always_comb begin
        next_state  = state;

        case (state)
            IDLE: begin
                if (rep)
                    next_state  = FORWARD;
            end

            FORWARD: begin
                if (tick && step_cnt == CW_STEPS-1)
                    next_state  = BACKWARD;
            end

            BACKWARD: begin
                if (tick && step_cnt == ACW_STEPS-1)
                    next_state  = rep ? FORWARD : DECAY;
            end

            DECAY: begin
                if (tick && all_off)
                    next_state  = IDLE;
            end
        endcase
    end
endmodule

tb/ring_flasher_tb.sv
`timescale 1ns/1ps

module ring_flasher_tb;
    import ring_flasher_pkg::*;

    // ── DUT interface ────────────────────────────────────────────
    logic clk, rst_n, rep;
    logic [NUM_LEDS-1:0] leds;

    ring_flasher dut (.clk, .rst_n, .rep, .leds);

    // 5 MHz → 200 ns period
    initial clk = 0;
    always #100 clk = ~clk;

    // ── Helpers ──────────────────────────────────────────────────
    int pass_cnt = 0, fail_cnt = 0;

    task automatic chk(input string msg, input logic cond);
        if (cond) begin
            $display("[PASS] %s", msg);
            pass_cnt++;
        end else begin
            $display("[FAIL] %s  (time=%0t)", msg, $time);
            fail_cnt++;
        end
    endtask

    // Chờ n tick thực sự từ counter (robust hơn đếm clock)
    task automatic wait_ticks(input int n);
        repeat(n) @(posedge clk iff dut.tick);
        #1; // cho non-blocking assignments settle
    endtask

    task automatic do_reset();
        rst_n = 0; rep = 0;
        repeat(4) @(posedge clk);
        @(negedge clk); rst_n = 1;
        #1;
    endtask

    function automatic logic all_zero();
        for (int i = 0; i < NUM_LEDS; i++)
            if (dut.led_brightness[i] != 0) return 0;
        return 1;
    endfunction

    // ── Test cases ───────────────────────────────────────────────
    initial begin
        $dumpfile("ring_flasher_tb.vcd");
        $dumpvars(0, ring_flasher_tb);

        // ── TC1: Reset ──────────────────────────────────────────
        $display("\n── TC1: Reset ──");
        do_reset();
        chk("TC1.1 state=IDLE",       dut.state   == IDLE);
        chk("TC1.2 pos_ptr=15",       dut.pos_ptr == NUM_LEDS - 1);
        chk("TC1.3 leds=0",           leds        == '0);
        chk("TC1.4 all brightness=0", all_zero());

        // ── TC2: IDLE hold (rep=0) ──────────────────────────────
        $display("\n── TC2: IDLE hold (rep=0) ──");
        wait_ticks(3);
        chk("TC2.1 still IDLE",     dut.state == IDLE);
        chk("TC2.2 leds still off", leds      == '0);

        // ── TC3: IDLE → FORWARD ─────────────────────────────────
        $display("\n── TC3: IDLE → FORWARD ──");
        @(negedge clk); rep = 1;
        @(posedge clk); #1;
        chk("TC3.1 state=FORWARD", dut.state == FORWARD);

        // ── TC4: FORWARD step 1 — led[0] sáng ──────────────────
        $display("\n── TC4: FORWARD step 1 ──");
        wait_ticks(1);
        chk("TC4.1 pos_ptr=0",              dut.pos_ptr           == 0);
        chk("TC4.2 led[0] brightness=max",  dut.led_brightness[0] == BRIGHTNESS_LEVELS);
        chk("TC4.3 led[1] brightness=0",    dut.led_brightness[1] == 0);

        // ── TC5: FORWARD step 2 — led[1] sáng, led[0] decay ────
        $display("\n── TC5: FORWARD step 2 ──");
        wait_ticks(1);
        chk("TC5.1 pos_ptr=1",              dut.pos_ptr           == 1);
        chk("TC5.2 led[1] brightness=max",  dut.led_brightness[1] == BRIGHTNESS_LEVELS);
        chk("TC5.3 led[0] decayed to 4",    dut.led_brightness[0] == BRIGHTNESS_LEVELS - 1);

        // ── TC6: FORWARD → BACKWARD sau đúng 12 step ───────────
        $display("\n── TC6: FORWARD → BACKWARD ──");
        wait_ticks(CW_STEPS - 2); // 2 tick đã đi rồi
        chk("TC6.1 state=BACKWARD",         dut.state                     == BACKWARD);
        chk("TC6.2 pos_ptr=11",             dut.pos_ptr                   == CW_STEPS - 1);
        chk("TC6.3 led[11] brightness=max", dut.led_brightness[CW_STEPS-1] == BRIGHTNESS_LEVELS);

        // ── TC7: BACKWARD step 1 ────────────────────────────────
        $display("\n── TC7: BACKWARD step 1 ──");
        wait_ticks(1);
        chk("TC7.1 pos_ptr=10",             dut.pos_ptr            == CW_STEPS - 2);
        chk("TC7.2 led[10] brightness=max", dut.led_brightness[10] == BRIGHTNESS_LEVELS);
        chk("TC7.3 led[11] decayed to 4",   dut.led_brightness[11] == BRIGHTNESS_LEVELS - 1);

        // ── TC8: BACKWARD → FORWARD (rep=1, loop) ───────────────
        $display("\n── TC8: BACKWARD → FORWARD loop (rep=1) ──");
        // rep=1 đã set, 1 BACKWARD tick xong, cần ACW_STEPS-1=7 tick nữa
        wait_ticks(ACW_STEPS - 1);
        chk("TC8.1 state=FORWARD", dut.state    == FORWARD);
        chk("TC8.2 step_cnt=0",    dut.step_cnt == 0);

        // ── TC9: BACKWARD → DECAY (rep=0) ───────────────────────
        $display("\n── TC9: BACKWARD → DECAY (rep=0) ──");
        wait_ticks(CW_STEPS);               // hoàn thành FORWARD thứ 2
        chk("TC9.0 entered BACKWARD", dut.state == BACKWARD);
        @(negedge clk); rep = 0;
        wait_ticks(ACW_STEPS);              // BACKWARD với rep=0
        chk("TC9.1 state=DECAY",      dut.state == DECAY);

        // ── TC10: DECAY → IDLE ──────────────────────────────────
        // max brightness vào DECAY = BRIGHTNESS_LEVELS = 5
        // cần 5 tick để về 0, tick thứ 6 để FSM register IDLE
        $display("\n── TC10: DECAY → IDLE ──");
        wait_ticks(BRIGHTNESS_LEVELS + 1);
        chk("TC10.1 state=IDLE",       dut.state == IDLE);
        chk("TC10.2 all brightness=0", all_zero());
        chk("TC10.3 leds all off",     leds      == '0);

        // ── TC11: PWM — brightness=5 → luôn on ─────────────────
        $display("\n── TC11: PWM max brightness ──");
        // Từ IDLE: start, chờ 1 step → led[0].brightness=5
        @(negedge clk); rep = 1;
        @(posedge clk); #1;
        wait_ticks(1);
        chk("TC11.0 led[0].brightness=5", dut.led_brightness[0] == BRIGHTNESS_LEVELS);
        begin
            int on_cnt = 0;
            repeat(BRIGHTNESS_LEVELS) begin
                @(posedge clk); #1;
                if (leds[0]) on_cnt++;
            end
            // brightness=5: 5>0,5>1,5>2,5>3,5>4 → all true → on 5/5
            chk("TC11.1 led[0] on 5/5 PWM cycles", on_cnt == BRIGHTNESS_LEVELS);
        end

        // ── TC12: PWM — brightness=0 → luôn off ─────────────────
        $display("\n── TC12: PWM zero brightness ──");
        // led[15] chưa bao giờ được lit (pos_ptr bắt đầu từ 0, mới đi 1 step)
        chk("TC12.0 led[15].brightness=0", dut.led_brightness[15] == 0);
        begin
            int on_cnt = 0;
            repeat(BRIGHTNESS_LEVELS) begin
                @(posedge clk); #1;
                if (leds[15]) on_cnt++;
            end
            // brightness=0: 0>0..4 → all false → off 5/5
            chk("TC12.1 led[15] off 5/5 PWM cycles", on_cnt == 0);
        end

        // ── Summary ─────────────────────────────────────────────
        $display("\n========== %0d passed, %0d failed ==========",
                 pass_cnt, fail_cnt);
        if (fail_cnt == 0) $display("ALL TESTS PASSED");
        $finish;
    end

    // Watchdog — nếu sim treo
    initial begin
        #(TICK_MAX * 200ns * (CW_STEPS*3 + ACW_STEPS*3 + BRIGHTNESS_LEVELS*2 + 20));
        $display("TIMEOUT: simulation hung");
        $finish;
    end

endmodule

ring_buffer/work/ring_flasher_tb.vcd
$date
   Tue Apr  7 10:23:55 2026
$end

$version
  2025.2
  $dumpfile ("ring_flasher_tb.vcd") 
$end

$timescale
  1ps
$end

$scope module ring_flasher_tb $end
$var reg 1 ! clk $end
$var reg 1 " rst_n $end
$var reg 1 # rep $end
$var reg 16 $ leds [15:0] $end
$var reg 32 % pass_cnt [31:0] $end
$var reg 32 & fail_cnt [31:0] $end
$scope module dut $end
$var wire 1 ' clk $end
$var wire 1 ( rst_n $end
$var wire 1 ) rep $end
$var reg 16 $ leds [15:0] $end
$var reg 2 * state $end
$var reg 2 + next_state $end
$var reg 1 , tick $end
$var reg 4 - step_cnt [3:0] $end
$var reg 4 . pos_ptr [3:0] $end
$var reg 4 / next_pos [3:0] $end
$var reg 1 0 all_off $end
$var reg 3 1 pwm_cnt [2:0] $end
$scope module u_counter $end
$var wire 1 ' clk $end
$var wire 1 ( rst_n $end
$var reg 1 , tick $end
$var reg 5 2 cnt [4:0] $end
$upscope $end
$scope begin Block85_5 $end
$var reg 32 3 i [31:0] $end
$upscope $end
$scope begin Block90_6 $end
$var reg 32 4 i [31:0] $end
$upscope $end
$scope begin Block99_7 $end
$var reg 32 5 i [31:0] $end
$upscope $end
$scope begin Block116_9 $end
$var reg 32 6 i [31:0] $end
$upscope $end
$upscope $end
$scope begin Block132_16 $end
$var reg 32 7 on_cnt [31:0] $end
$upscope $end
$scope begin Block146_17 $end
$var reg 32 8 on_cnt [31:0] $end
$upscope $end
$scope task chk $end
$upscope $end
$scope task wait_ticks $end
$upscope $end
$scope task do_reset $end
$upscope $end
$scope function all_zero $end
$upscope $end
$upscope $end
$enddefinitions $end

#0
$dumpvars
0!
0"
0#
b0 $
b0 %
b0 &
0'
0(
0)
b0 *
b0 +
0,
b0 -
b1111 .
b1111 /
10
b0 1
b0 2
b10000 3
b0 4
b0 5
b10000 6
b0 7
b0 8
$end

#100000
1!
1'
b10000 3

#200000
0!
0'

#300000
1!
1'
b10000 3

#400000
0!
0'

#500000
1!
1'
b10000 3

#600000
0!
0'

#700000
1!
1'
b10000 3

#800000
0!
1"
0'
1(

#801000
b100 %

#900000
1!
1'
b1 1
b1 2

#1000000
0!
0'

#1100000
1!
1'
b10 1
b10 2

#1200000
0!
0'

#1300000
1!
1'
b11 1
b11 2

#1400000
0!
0'

#1500000
1!
1'
b100 1
b100 2

#1600000
0!
0'

#1700000
1!
1'
b0 1
b101 2

#1800000
0!
0'

#1900000
1!
1'
b1 1
b110 2

#2000000
0!
0'

#2100000
1!
1'
b10 1
b111 2

#2200000
0!
0'

#2300000
1!
1'
b11 1
b1000 2

#2400000
0!
0'

#2500000
1!
1'
b100 1
b1001 2

#2600000
0!
0'

#2700000
1!
1'
b0 1
b1010 2

#2800000
0!
0'

#2900000
1!
1'
b1 1
b1011 2

#3000000
0!
0'

#3100000
1!
1'
b10 1
b1100 2

#3200000
0!
0'

#3300000
1!
1'
b11 1
b1101 2

#3400000
0!
0'

#3500000
1!
1'
b100 1
b1110 2

#3600000
0!
0'

#3700000
1!
1'
b0 1
b1111 2

#3800000
0!
0'

#3900000
1!
1'
b1 1
b10000 2

#4000000
0!
0'

#4100000
1!
1'
b10 1
b10001 2

#4200000
0!
0'

#4300000
1!
1'
b11 1
b10010 2

#4400000
0!
0'

#4500000
1!
1'
1,
b100 1
b10011 2

#4600000
0!
0'

#4700000
1!
1'
0,
b1 -
b0 1
b0 2

#4800000
0!
0'

#4900000
1!
1'
b1 1
b1 2

#5000000
0!
0'

#5100000
1!
1'
b10 1
b10 2

#5200000
0!
0'

#5300000
1!
1'
b11 1
b11 2

#5400000
0!
0'

#5500000
1!
1'
b100 1
b100 2

#5600000
0!
0'

#5700000
1!
1'
b0 1
b101 2

#5800000
0!
0'

#5900000
1!
1'
b1 1
b110 2

#6000000
0!
0'

#6100000
1!
1'
b10 1
b111 2

#6200000
0!
0'

#6300000
1!
1'
b11 1
b1000 2

#6400000
0!
0'

#6500000
1!
1'
b100 1
b1001 2

#6600000
0!
0'

#6700000
1!
1'
b0 1
b1010 2

#6800000
0!
0'

#6900000
1!
1'
b1 1
b1011 2

#7000000
0!
0'

#7100000
1!
1'
b10 1
b1100 2

#7200000
0!
0'

#7300000
1!
1'
b11 1
b1101 2

#7400000
0!
0'

#7500000
1!
1'
b100 1
b1110 2

#7600000
0!
0'

#7700000
1!
1'
b0 1
b1111 2

#7800000
0!
0'

#7900000
1!
1'
b1 1
b10000 2

#8000000
0!
0'

#8100000
1!
1'
b10 1
b10001 2

#8200000
0!
0'

#8300000
1!
1'
b11 1
b10010 2

#8400000
0!
0'

#8500000
1!
1'
1,
b100 1
b10011 2

#8600000
0!
0'

#8700000
1!
1'
0,
b10 -
b0 1
b0 2

#8800000
0!
0'

#8900000
1!
1'
b1 1
b1 2

#9000000
0!
0'

#9100000
1!
1'
b10 1
b10 2

#9200000
0!
0'

#9300000
1!
1'
b11 1
b11 2

#9400000
0!
0'

#9500000
1!
1'
b100 1
b100 2

#9600000
0!
0'

#9700000
1!
1'
b0 1
b101 2

#9800000
0!
0'

#9900000
1!
1'
b1 1
b110 2

#10000000
0!
0'

#10100000
1!
1'
b10 1
b111 2

#10200000
0!
0'

#10300000
1!
1'
b11 1
b1000 2

#10400000
0!
0'

#10500000
1!
1'
b100 1
b1001 2

#10600000
0!
0'

#10700000
1!
1'
b0 1
b1010 2

#10800000
0!
0'

#10900000
1!
1'
b1 1
b1011 2

#11000000
0!
0'

#11100000
1!
1'
b10 1
b1100 2

#11200000
0!
0'

#11300000
1!
1'
b11 1
b1101 2

#11400000
0!
0'

#11500000
1!
1'
b100 1
b1110 2

#11600000
0!
0'

#11700000
1!
1'
b0 1
b1111 2

#11800000
0!
0'

#11900000
1!
1'
b1 1
b10000 2

#12000000
0!
0'

#12100000
1!
1'
b10 1
b10001 2

#12200000
0!
0'

#12300000
1!
1'
b11 1
b10010 2

#12400000
0!
0'

#12500000
1!
1'
1,
b100 1
b10011 2

#12600000
0!
0'

#12700000
1!
1'
0,
b11 -
b0 1
b0 2

#12701000
b110 %

#12800000
0!
1#
0'
1)
b1 +

#12900000
1!
1'
b1 *
b0 /
b1 1
b1 2

#12901000
b111 %

#13000000
0!
0'

#13100000
1!
1'
b10 1
b10 2

#13200000
0!
0'

#13300000
1!
1'
b11 1
b11 2

#13400000
0!
0'

#13500000
1!
1'
b100 1
b100 2

#13600000
0!
0'

#13700000
1!
1'
b0 1
b101 2

#13800000
0!
0'

#13900000
1!
1'
b1 1
b110 2

#14000000
0!
0'

#14100000
1!
1'
b10 1
b111 2

#14200000
0!
0'

#14300000
1!
1'
b11 1
b1000 2

#14400000
0!
0'

#14500000
1!
1'
b100 1
b1001 2

#14600000
0!
0'

#14700000
1!
1'
b0 1
b1010 2

#14800000
0!
0'

#14900000
1!
1'
b1 1
b1011 2

#15000000
0!
0'

#15100000
1!
1'
b10 1
b1100 2

#15200000
0!
0'

#15300000
1!
1'
b11 1
b1101 2

#15400000
0!
0'

#15500000
1!
1'
b100 1
b1110 2

#15600000
0!
0'

#15700000
1!
1'
b0 1
b1111 2

#15800000
0!
0'

#15900000
1!
1'
b1 1
b10000 2

#16000000
0!
0'

#16100000
1!
1'
b10 1
b10001 2

#16200000
0!
0'

#16300000
1!
1'
b11 1
b10010 2

#16400000
0!
0'

#16500000
1!
1'
1,
b100 1
b10011 2

#16600000
0!
0'

#16700000
1!
b1 $
1'
0,
b100 -
b0 .
b1 /
00
b0 1
b0 2
b10000 4
b10000 6

#16701000
b1010 %

#16800000
0!
0'

#16900000
1!
1'
b1 1
b1 2

#17000000
0!
0'

#17100000
1!
1'
b10 1
b10 2

#17200000
0!
0'

#17300000
1!
1'
b11 1
b11 2

#17400000
0!
0'

#17500000
1!
1'
b100 1
b100 2

#17600000
0!
0'

#17700000
1!
1'
b0 1
b101 2

#17800000
0!
0'

#17900000
1!
1'
b1 1
b110 2

#18000000
0!
0'

#18100000
1!
1'
b10 1
b111 2

#18200000
0!
0'

#18300000
1!
1'
b11 1
b1000 2

#18400000
0!
0'

#18500000
1!
1'
b100 1
b1001 2

#18600000
0!
0'

#18700000
1!
1'
b0 1
b1010 2

#18800000
0!
0'

#18900000
1!
1'
b1 1
b1011 2

#19000000
0!
0'

#19100000
1!
1'
b10 1
b1100 2

#19200000
0!
0'

#19300000
1!
1'
b11 1
b1101 2

#19400000
0!
0'

#19500000
1!
1'
b100 1
b1110 2

#19600000
0!
0'

#19700000
1!
1'
b0 1
b1111 2

#19800000
0!
0'

#19900000
1!
1'
b1 1
b10000 2

#20000000
0!
0'

#20100000
1!
1'
b10 1
b10001 2

#20200000
0!
0'

#20300000
1!
1'
b11 1
b10010 2

#20400000
0!
0'

#20500000
1!
1'
1,
b100 1
b10011 2

#20600000
0!
0'

#20700000
1!
b11 $
1'
0,
b101 -
b1 .
b10 /
00
b0 1
b0 2
b10000 4
b10000 6

#20701000
b1101 %

#20800000
0!
0'

#20900000
1!
1'
b1 1
b1 2

#21000000
0!
0'

#21100000
1!
1'
b10 1
b10 2

#21200000
0!
0'

#21300000
1!
1'
b11 1
b11 2

#21400000
0!
0'

#21500000
1!
b10 $
1'
b100 1
b100 2

#21600000
0!
0'

#21700000
1!
b11 $
1'
b0 1
b101 2

#21800000
0!
0'

#21900000
1!
1'
b1 1
b110 2

#22000000
0!
0'

#22100000
1!
1'
b10 1
b111 2

#22200000
0!
0'

#22300000
1!
1'
b11 1
b1000 2

#22400000
0!
0'

#22500000
1!
b10 $
1'
b100 1
b1001 2

#22600000
0!
0'

#22700000
1!
b11 $
1'
b0 1
b1010 2

#22800000
0!
0'

#22900000
1!
1'
b1 1
b1011 2

#23000000
0!
0'

#23100000
1!
1'
b10 1
b1100 2

#23200000
0!
0'

#23300000
1!
1'
b11 1
b1101 2

#23400000
0!
0'

#23500000
1!
b10 $
1'
b100 1
b1110 2

#23600000
0!
0'

#23700000
1!
b11 $
1'
b0 1
b1111 2

#23800000
0!
0'

#23900000
1!
1'
b1 1
b10000 2

#24000000
0!
0'

#24100000
1!
1'
b10 1
b10001 2

#24200000
0!
0'

#24300000
1!
1'
b11 1
b10010 2

#24400000
0!
0'

#24500000
1!
b10 $
1'
1,
b100 1
b10011 2

#24600000
0!
0'

#24700000
1!
b111 $
1'
0,
b110 -
b10 .
b11 /
00
b0 1
b0 2
b10000 4
b10000 6

#24800000
0!
0'

#24900000
1!
1'
b1 1
b1 2

#25000000
0!
0'

#25100000
1!
1'
b10 1
b10 2

#25200000
0!
0'

#25300000
1!
b110 $
1'
b11 1
b11 2

#25400000
0!
0'

#25500000
1!
b100 $
1'
b100 1
b100 2

#25600000
0!
0'

#25700000
1!
b111 $
1'
b0 1
b101 2

#25800000
0!
0'

#25900000
1!
1'
b1 1
b110 2

#26000000
0!
0'

#26100000
1!
1'
b10 1
b111 2

#26200000
0!
0'

#26300000
1!
b110 $
1'
b11 1
b1000 2

#26400000
0!
0'

#26500000
1!
b100 $
1'
b100 1
b1001 2

#26600000
0!
0'

#26700000
1!
b111 $
1'
b0 1
b1010 2

#26800000
0!
0'

#26900000
1!
1'
b1 1
b1011 2

#27000000
0!
0'

#27100000
1!
1'
b10 1
b1100 2

#27200000
0!
0'

#27300000
1!
b110 $
1'
b11 1
b1101 2

#27400000
0!
0'

#27500000
1!
b100 $
1'
b100 1
b1110 2

#27600000
0!
0'

#27700000
1!
b111 $
1'
b0 1
b1111 2

#27800000
0!
0'

#27900000
1!
1'
b1 1
b10000 2

#28000000
0!
0'

#28100000
1!
1'
b10 1
b10001 2

#28200000
0!
0'

#28300000
1!
b110 $
1'
b11 1
b10010 2

#28400000
0!
0'

#28500000
1!
b100 $
1'
1,
b100 1
b10011 2

#28600000
0!
0'

#28700000
1!
b1111 $
1'
0,
b111 -
b11 .
b100 /
00
b0 1
b0 2
b10000 4
b10000 6

#28800000
0!
0'

#28900000
1!
1'
b1 1
b1 2

#29000000
0!
0'

#29100000
1!
b1110 $
1'
b10 1
b10 2

#29200000
0!
0'

#29300000
1!
b1100 $
1'
b11 1
b11 2

#29400000
0!
0'

#29500000
1!
b1000 $
1'
b100 1
b100 2

#29600000
0!
0'

#29700000
1!
b1111 $
1'
b0 1
b101 2

#29800000
0!
0'

#29900000
1!
1'
b1 1
b110 2

#30000000
0!
0'

#30100000
1!
b1110 $
1'
b10 1
b111 2

#30200000
0!
0'

#30300000
1!
b1100 $
1'
b11 1
b1000 2

#30400000
0!
0'

#30500000
1!
b1000 $
1'
b100 1
b1001 2

#30600000
0!
0'

#30700000
1!
b1111 $
1'
b0 1
b1010 2

#30800000
0!
0'

#30900000
1!
1'
b1 1
b1011 2

#31000000
0!
0'

#31100000
1!
b1110 $
1'
b10 1
b1100 2

#31200000
0!
0'

#31300000
1!
b1100 $
1'
b11 1
b1101 2

#31400000
0!
0'

#31500000
1!
b1000 $
1'
b100 1
b1110 2

#31600000
0!
0'

#31700000
1!
b1111 $
1'
b0 1
b1111 2

#31800000
0!
0'

#31900000
1!
1'
b1 1
b10000 2

#32000000
0!
0'

#32100000
1!
b1110 $
1'
b10 1
b10001 2

#32200000
0!
0'

#32300000
1!
b1100 $
1'
b11 1
b10010 2

#32400000
0!
0'

#32500000
1!
b1000 $
1'
1,
b100 1
b10011 2

#32600000
0!
0'

#32700000
1!
b11111 $
1'
0,
b1000 -
b100 .
b101 /
00
b0 1
b0 2
b10000 4
b10000 6

#32800000
0!
0'

#32900000
1!
b11110 $
1'
b1 1
b1 2

#33000000
0!
0'

#33100000
1!
b11100 $
1'
b10 1
b10 2

#33200000
0!
0'

#33300000
1!
b11000 $
1'
b11 1
b11 2

#33400000
0!
0'

#33500000
1!
b10000 $
1'
b100 1
b100 2

#33600000
0!
0'

#33700000
1!
b11111 $
1'
b0 1
b101 2

#33800000
0!
0'

#33900000
1!
b11110 $
1'
b1 1
b110 2

#34000000
0!
0'

#34100000
1!
b11100 $
1'
b10 1
b111 2

#34200000
0!
0'

#34300000
1!
b11000 $
1'
b11 1
b1000 2

#34400000
0!
0'

#34500000
1!
b10000 $
1'
b100 1
b1001 2

#34600000
0!
0'

#34700000
1!
b11111 $
1'
b0 1
b1010 2

#34800000
0!
0'

#34900000
1!
b11110 $
1'
b1 1
b1011 2

#35000000
0!
0'

#35100000
1!
b11100 $
1'
b10 1
b1100 2

#35200000
0!
0'

#35300000
1!
b11000 $
1'
b11 1
b1101 2

#35400000
0!
0'

#35500000
1!
b10000 $
1'
b100 1
b1110 2

#35600000
0!
0'

#35700000
1!
b11111 $
1'
b0 1
b1111 2

#35800000
0!
0'

#35900000
1!
b11110 $
1'
b1 1
b10000 2

#36000000
0!
0'

#36100000
1!
b11100 $
1'
b10 1
b10001 2

#36200000
0!
0'

#36300000
1!
b11000 $
1'
b11 1
b10010 2

#36400000
0!
0'

#36500000
1!
b10000 $
1'
1,
b100 1
b10011 2

#36600000
0!
0'

#36700000
1!
b111110 $
1'
0,
b1001 -
b101 .
b110 /
00
b0 1
b0 2
b10000 4
b10000 6

#36800000
0!
0'

#36900000
1!
b111100 $
1'
b1 1
b1 2

#37000000
0!
0'

#37100000
1!
b111000 $
1'
b10 1
b10 2

#37200000
0!
0'

#37300000
1!
b110000 $
1'
b11 1
b11 2

#37400000
0!
0'

#37500000
1!
b100000 $
1'
b100 1
b100 2

#37600000
0!
0'

#37700000
1!
b111110 $
1'
b0 1
b101 2

#37800000
0!
0'

#37900000
1!
b111100 $
1'
b1 1
b110 2

#38000000
0!
0'

#38100000
1!
b111000 $
1'
b10 1
b111 2

#38200000
0!
0'

#38300000
1!
b110000 $
1'
b11 1
b1000 2

#38400000
0!
0'

#38500000
1!
b100000 $
1'
b100 1
b1001 2

#38600000
0!
0'

#38700000
1!
b111110 $
1'
b0 1
b1010 2

#38800000
0!
0'

#38900000
1!
b111100 $
1'
b1 1
b1011 2

#39000000
0!
0'

#39100000
1!
b111000 $
1'
b10 1
b1100 2

#39200000
0!
0'

#39300000
1!
b110000 $
1'
b11 1
b1101 2

#39400000
0!
0'

#39500000
1!
b100000 $
1'
b100 1
b1110 2

#39600000
0!
0'

#39700000
1!
b111110 $
1'
b0 1
b1111 2

#39800000
0!
0'

#39900000
1!
b111100 $
1'
b1 1
b10000 2

#40000000
0!
0'

#40100000
1!
b111000 $
1'
b10 1
b10001 2

#40200000
0!
0'

#40300000
1!
b110000 $
1'
b11 1
b10010 2

#40400000
0!
0'

#40500000
1!
b100000 $
1'
1,
b100 1
b10011 2

#40600000
0!
0'

#40700000
1!
b1111100 $
1'
0,
b1010 -
b110 .
b111 /
00
b0 1
b0 2
b10000 4
b10000 6

#40800000
0!
0'

#40900000
1!
b1111000 $
1'
b1 1
b1 2

#41000000
0!
0'

#41100000
1!
b1110000 $
1'
b10 1
b10 2

#41200000
0!
0'

#41300000
1!
b1100000 $
1'
b11 1
b11 2

#41400000
0!
0'

#41500000
1!
b1000000 $
1'
b100 1
b100 2

#41600000
0!
0'

#41700000
1!
b1111100 $
1'
b0 1
b101 2

#41800000
0!
0'

#41900000
1!
b1111000 $
1'
b1 1
b110 2

#42000000
0!
0'

#42100000
1!
b1110000 $
1'
b10 1
b111 2

#42200000
0!
0'

#42300000
1!
b1100000 $
1'
b11 1
b1000 2

#42400000
0!
0'

#42500000
1!
b1000000 $
1'
b100 1
b1001 2

#42600000
0!
0'

#42700000
1!
b1111100 $
1'
b0 1
b1010 2

#42800000
0!
0'

#42900000
1!
b1111000 $
1'
b1 1
b1011 2

#43000000
0!
0'

#43100000
1!
b1110000 $
1'
b10 1
b1100 2

#43200000
0!
0'

#43300000
1!
b1100000 $
1'
b11 1
b1101 2

#43400000
0!
0'

#43500000
1!
b1000000 $
1'
b100 1
b1110 2

#43600000
0!
0'

#43700000
1!
b1111100 $
1'
b0 1
b1111 2

#43800000
0!
0'

#43900000
1!
b1111000 $
1'
b1 1
b10000 2

#44000000
0!
0'

#44100000
1!
b1110000 $
1'
b10 1
b10001 2

#44200000
0!
0'

#44300000
1!
b1100000 $
1'
b11 1
b10010 2

#44400000
0!
0'

#44500000
1!
b1000000 $
1'
1,
b100 1
b10011 2

#44600000
0!
0'

#44700000
1!
b11111000 $
1'
0,
b1011 -
b111 .
b1000 /
00
b0 1
b0 2
b10000 4
b10000 6

#44800000
0!
0'

#44900000
1!
b11110000 $
1'
b1 1
b1 2

#45000000
0!
0'

#45100000
1!
b11100000 $
1'
b10 1
b10 2

#45200000
0!
0'

#45300000
1!
b11000000 $
1'
b11 1
b11 2

#45400000
0!
0'

#45500000
1!
b10000000 $
1'
b100 1
b100 2

#45600000
0!
0'

#45700000
1!
b11111000 $
1'
b0 1
b101 2

#45800000
0!
0'

#45900000
1!
b11110000 $
1'
b1 1
b110 2

#46000000
0!
0'

#46100000
1!
b11100000 $
1'
b10 1
b111 2

#46200000
0!
0'

#46300000
1!
b11000000 $
1'
b11 1
b1000 2

#46400000
0!
0'

#46500000
1!
b10000000 $
1'
b100 1
b1001 2

#46600000
0!
0'

#46700000
1!
b11111000 $
1'
b0 1
b1010 2

#46800000
0!
0'

#46900000
1!
b11110000 $
1'
b1 1
b1011 2

#47000000
0!
0'

#47100000
1!
b11100000 $
1'
b10 1
b1100 2

#47200000
0!
0'

#47300000
1!
b11000000 $
1'
b11 1
b1101 2

#47400000
0!
0'

#47500000
1!
b10000000 $
1'
b100 1
b1110 2

#47600000
0!
0'

